{
  "schemaVersion": 1,
  "id": "cm",
  "version": "1.0.1",

  "name": "Coal Tools Mod",
  "description": "A mod that adds various coal tools and items",
  "authors": [
    "Mega2447"
  ],
  "contact": {
    "homepage": "https://www.curseforge.com/minecraft/mc-mods/coal-tools-mod",
    "sources": "https://github.com/MegaSatan/Coal-Tools-Mod/tree/1.16.4-fabric"
  },

  "license": "CC0-1.0",

  "environment": "*",
  "entrypoints": {
    "main": [
      "mod.Mega2447.coal.CoalToolsMod"
    ]
  },
  "mixins": [
    "modid.mixins.json"
  ],

  "depends": {
    "fabricloader": ">=0.7.4",
    "fabric": "*",
    "minecraft": "1.16.x"
  },
  "suggests": {
    "another-mod": "*"
  }
}
